{"data":[{"bn":"R607","report_type":"YABC","year":2011,"metric":"grad_pct_6_all","rank":61},{"bn":"R607","report_type":"YABC","year":2012,"metric":"grad_pct_6_all","rank":86},{"bn":"R607","report_type":"YABC","year":2013,"metric":"grad_pct_6_all","rank":70},{"bn":"R607","report_type":"YABC","year":2014,"metric":"grad_pct_6_all","rank":95},{"bn":"R607","report_type":"YABC","year":2015,"metric":"grad_pct_6_all","rank":68},{"bn":"R607","report_type":"YABC","year":2016,"metric":"grad_pct_6_all","rank":78},{"bn":"R607","report_type":"YABC","year":2017,"metric":"grad_pct_6_all","rank":39},{"bn":"R607","report_type":"YABC","year":2018,"metric":"grad_pct_6_all","rank":57}]}