{"data":[{"bn":"M375","report_type":"EMS","year":2009,"metric":"prof_pct_ela_all","rank":0},{"bn":"M375","report_type":"EMS","year":2010,"metric":"prof_pct_ela_all","rank":2},{"bn":"M375","report_type":"EMS","year":2011,"metric":"prof_pct_ela_all","rank":4},{"bn":"M375","report_type":"EMS","year":2012,"metric":"prof_pct_ela_all","rank":10},{"bn":"M375","report_type":"EMS","year":2013,"metric":"prof_pct_ela_all","rank":5},{"bn":"M375","report_type":"EMS","year":2014,"metric":"prof_pct_ela_all","rank":13},{"bn":"M375","report_type":"EMS","year":2015,"metric":"prof_pct_ela_all","rank":17},{"bn":"M375","report_type":"EMS","year":2016,"metric":"prof_pct_ela_all","rank":13},{"bn":"M375","report_type":"EMS","year":2017,"metric":"prof_pct_ela_all","rank":14},{"bn":"M375","report_type":"EMS","year":2009,"metric":"prof_pct_mth_all","rank":1},{"bn":"M375","report_type":"EMS","year":2010,"metric":"prof_pct_mth_all","rank":1},{"bn":"M375","report_type":"EMS","year":2011,"metric":"prof_pct_mth_all","rank":1},{"bn":"M375","report_type":"EMS","year":2012,"metric":"prof_pct_mth_all","rank":21},{"bn":"M375","report_type":"EMS","year":2013,"metric":"prof_pct_mth_all","rank":8},{"bn":"M375","report_type":"EMS","year":2014,"metric":"prof_pct_mth_all","rank":5},{"bn":"M375","report_type":"EMS","year":2015,"metric":"prof_pct_mth_all","rank":12},{"bn":"M375","report_type":"EMS","year":2016,"metric":"prof_pct_mth_all","rank":29},{"bn":"M375","report_type":"EMS","year":2017,"metric":"prof_pct_mth_all","rank":12},{"bn":"M375","report_type":"EMS","year":2018,"metric":"prof_pct_ela_all","rank":27},{"bn":"M375","report_type":"EMS","year":2018,"metric":"prof_pct_mth_all","rank":14}]}